Metadata-Version: 2.1
Name: shutils
Version: 0.0.9
Summary: Tools for python development.
Home-page: https://github.com/shannan1989/py-shutils
Author: 山南
Author-email: zhangpeichaook@163.com
License: MIT
Platform: UNKNOWN
